flasksecforge/__init__.py
flasksecforge/cli.py
flasksecforge/templates/flask_api_boilerplate/.env
flasksecforge/templates/flask_api_boilerplate/README.md
flasksecforge/templates/flask_api_boilerplate/gunicorn.conf.py
flasksecforge/templates/flask_api_boilerplate/requirements.txt
flasksecforge/templates/flask_api_boilerplate/run.py
flasksecforge/templates/flask_api_boilerplate/app/__init__.py
flasksecforge/templates/flask_api_boilerplate/app/config.py
flasksecforge/templates/flask_api_boilerplate/app/extensions.py
flasksecforge/templates/flask_api_boilerplate/app/models.py
flasksecforge/templates/flask_api_boilerplate/app/schemas.py
flasksecforge/templates/flask_api_boilerplate/app/blueprints/__init__.py
flasksecforge/templates/flask_api_boilerplate/app/blueprints/auth/__init__.py
flasksecforge/templates/flask_api_boilerplate/app/blueprints/auth/views.py
flasksecforge/templates/flask_api_boilerplate/app/blueprints/items/__init__.py
flasksecforge/templates/flask_api_boilerplate/app/blueprints/items/views.py
flasksecforge/templates/flask_api_boilerplate/app/blueprints/users/__init__.py
flasksecforge/templates/flask_api_boilerplate/app/blueprints/users/views.py
flasksecforge-0.1.3.dist-info/LICENSE.md
flasksecforge-0.1.3.dist-info/METADATA
flasksecforge-0.1.3.dist-info/WHEEL
flasksecforge-0.1.3.dist-info/entry_points.txt
flasksecforge-0.1.3.dist-info/top_level.txt
flasksecforge-0.1.3.dist-info/RECORD
