Metadata-Version: 2.1
Name: flasksecforge
Version: 0.1.3
Summary: Scaffold a Flask‑secure boilerplate API.
Home-page: https://github.com/reprompts/flasksecforge
Author: RePromptsQuest
Author-email: repromptsquest@gmail.com
License: MIT
Classifier: Programming Language :: Python :: 3
Classifier: License :: OSI Approved :: MIT License
Classifier: Operating System :: OS Independent
Requires-Python: >=3.6
License-File: LICENSE.md
Requires-Dist: click
Requires-Dist: Flask>=2.0
Requires-Dist: Flask-Migrate>=3.1
Requires-Dist: Flask-JWT-Extended>=4.4
Requires-Dist: Flask-Cors>=3.0
Requires-Dist: Flask-SQLAlchemy>=2.5
Requires-Dist: python-dotenv>=0.19.0
Requires-Dist: marshmallow>=3.0
Requires-Dist: marshmallow-sqlalchemy>=0.23.0
Requires-Dist: gunicorn>=20.0
